{
    "CompUnits": {
        "v7YNK_d": {
            "checksum": 0,
            "text": 364,
            "mod": "accum_if",
            "out": "v7YNK_d.o",
            "bytes": 11748,
            "mode": 4,
            "archive": "archive.0/_115596_archive_1.a"
        },
        "amcQw_d": {
            "checksum": 0,
            "text": 618,
            "mod": "...MASTER...",
            "out": "objs/amcQw_d.o",
            "bytes": 9238,
            "mode": 4
        },
        "hEeZs_d": {
            "checksum": 0,
            "text": 2015678,
            "mod": "vcs_paramclassrepository",
            "out": "hEeZs_d.o",
            "bytes": 6778422,
            "cls": 1980093,
            "mode": 4,
            "archive": "archive.0/_115596_archive_1.a"
        },
        "nhiwz_d": {
            "checksum": 0,
            "text": 74342,
            "mod": "uvm_custom_install_recording",
            "out": "nhiwz_d.o",
            "bytes": 358016,
            "cls": 49853,
            "mode": 4,
            "archive": "archive.0/_115596_archive_1.a"
        },
        "W0eJz_d": {
            "checksum": 0,
            "text": 5346,
            "mod": "top_tb",
            "out": "W0eJz_d.o",
            "bytes": 21494,
            "mode": 4,
            "archive": "archive.0/_115596_archive_1.a"
        },
        "uM9F1_d": {
            "checksum": 0,
            "text": 4512,
            "mod": "_vcs_DPI_package",
            "out": "uM9F1_d.o",
            "bytes": 19492,
            "mode": 4,
            "archive": "archive.0/_115596_archive_1.a"
        },
        "pjuRd_d": {
            "checksum": 0,
            "text": 55708,
            "mod": "_vcs_unit__657117652",
            "out": "pjuRd_d.o",
            "bytes": 226384,
            "cls": 53551,
            "mode": 4,
            "archive": "archive.0/_115596_archive_1.a"
        },
        "reYIK_d": {
            "checksum": 0,
            "text": 7441,
            "mod": "std",
            "out": "reYIK_d.o",
            "bytes": 44340,
            "cls": 7024,
            "mode": 4,
            "archive": "archive.0/_115596_archive_1.a"
        },
        "zr7M1_d": {
            "checksum": 0,
            "text": 2255850,
            "mod": "uvm_pkg",
            "out": "zr7M1_d.o",
            "bytes": 6000804,
            "cls": 2145189,
            "mode": 4,
            "archive": "archive.0/_115596_archive_1.a"
        },
        "zQBzV_d": {
            "checksum": 0,
            "text": 460,
            "mod": "_vcs_msglog",
            "out": "zQBzV_d.o",
            "bytes": 10666,
            "mode": 4,
            "archive": "archive.0/_115596_archive_1.a"
        },
        "EbjT3_d": {
            "checksum": 0,
            "text": 478822,
            "mod": "uvm_custom_install_verdi_recording",
            "out": "EbjT3_d.o",
            "bytes": 1236402,
            "cls": 298487,
            "mode": 4,
            "archive": "archive.0/_115596_archive_1.a"
        },
        "DiISD_d": {
            "checksum": 0,
            "text": 1339,
            "mod": "accum",
            "out": "DiISD_d.o",
            "bytes": 9460,
            "mode": 4,
            "archive": "archive.0/_115596_archive_1.a"
        }
    },
    "Modules": {
        "...MASTER...": {
            "start_perf": [
                3.6424529552459717,
                3.311734,
                0.199742,
                341104,
                348372,
                1658908885.2743239,
                304737939180390
            ],
            "child_modules": {
                "uvm_custom_install_recording": 1,
                "top_tb": 1,
                "uvm_pkg": 1,
                "uvm_custom_install_verdi_recording": 1,
                "vcs_paramclassrepository": 1,
                "std": 1,
                "_vcs_msglog": 1,
                "_vcs_unit__657117652": 1,
                "_vcs_DPI_package": 1
            },
            "nMops": 0,
            "end_perf": [
                3.6445250511169434,
                3.3136860000000001,
                0.19986000000000001,
                342084,
                348372,
                304737945209780,
                0,
                0
            ],
            "nQuads": 0,
            "nRouts": 5
        },
        "_vcs_unit__657117652": {
            "start_perf": [
                4.7616169452667236,
                4.372922,
                0.25581900000000002,
                349244,
                349244,
                1658908886.3934879,
                304741178821329
            ],
            "svclass": [
                "accum_transaction",
                12747,
                1080,
                10,
                9,
                4294974329,
                "accum_monitor",
                17232,
                1718,
                42,
                11,
                4294974414,
                "accum_agent",
                5955,
                436,
                8,
                8,
                4294974481,
                "accum_env",
                6347,
                486,
                8,
                8,
                4294974637,
                "base_test",
                5942,
                372,
                9,
                9,
                4294974671,
                "my_case1",
                5328,
                305,
                8,
                8,
                4294974744
            ],
            "child_modules": {},
            "Compiled Times": 1,
            "Compiled": "Yes",
            "end_perf": [
                4.7977960109710693,
                4.4046019999999997,
                0.26003500000000002,
                349244,
                349244,
                304741283629301,
                4294967297,
                0
            ],
            "nMops": 4565,
            "nQuads": 1412,
            "nRouts": 110
        },
        "_vcs_DPI_package": {
            "start_perf": [
                4.7572510242462158,
                4.3687839999999998,
                0.25581100000000001,
                349244,
                349244,
                1658908886.389122,
                304741166200964
            ],
            "child_modules": {},
            "Compiled Times": 1,
            "Compiled": "Yes",
            "nMops": 254,
            "end_perf": [
                4.7615740299224854,
                4.3728809999999996,
                0.25581700000000002,
                349244,
                349244,
                304741178766548,
                0,
                0
            ],
            "nQuads": 123,
            "nRouts": 12
        },
        "vcs_paramclassrepository": {
            "start_perf": [
                3.6446590423583984,
                3.313787,
                0.19986599999999999,
                342084,
                348372,
                1658908885.27653,
                304737945567727
            ],
            "svclass": [
                "std_mailbox_42816961243213493938_65",
                1757,
                136,
                9,
                9,
                0,
                "std_mailbox_36951920133088784204_34",
                1757,
                136,
                9,
                9,
                0,
                "std_mailbox_2190068584822684823_31",
                1757,
                136,
                9,
                9,
                0,
                "std_mailbox_11784808032147832686_39",
                1757,
                136,
                9,
                9,
                0,
                "uvm_pkg_uvm_sequencer_param_base_24844159852957008461_78",
                22342,
                2029,
                19,
                19,
                12884937374,
                "uvm_pkg_uvm_sequencer_param_base_27081641443397297811_68",
                24184,
                2168,
                19,
                19,
                12884937374,
                "uvm_pkg_uvm_sequencer_param_base_2437592303813233279_130",
                24184,
                2168,
                19,
                19,
                12884937374,
                "uvm_pkg_uvm_sequencer_24844159852957008461_78",
                8182,
                420,
                15,
                15,
                12884937838,
                "uvm_pkg_uvm_sequencer_27081641443397297811_68",
                12181,
                883,
                21,
                15,
                12884937838,
                "uvm_pkg_uvm_sequencer_2437592303813233279_130",
                11510,
                824,
                18,
                15,
                12884937838,
                "_vcs_unit__657117652_accum_sequencer_11_0",
                3012,
                168,
                6,
                6,
                4294974345,
                "uvm_pkg_uvm_driver_24844159852957008461_78",
                1759,
                115,
                4,
                4,
                12884934671,
                "uvm_pkg_uvm_driver_2437592303813233279_130",
                3444,
                335,
                4,
                4,
                12884934671,
                "_vcs_unit__657117652_accum_driver_11_0",
                17500,
                1673,
                49,
                11,
                4294974358,
                "_vcs_unit__657117652_accum_predictor_11_0",
                6845,
                539,
                9,
                9,
                4294974510,
                "uvm_pkg_uvm_port_base_29345012303560527042_103",
                37326,
                3098,
                26,
                26,
                12884930691,
                "uvm_pkg_uvm_port_base_39390923434110787983_103",
                23795,
                1927,
                26,
                26,
                12884930691,
                "uvm_pkg_uvm_port_base_21996234534275348455_93",
                37326,
                3098,
                26,
                26,
                12884930691,
                "uvm_pkg_uvm_port_base_22000921013756544682_93",
                23795,
                1927,
                26,
                26,
                12884930691,
                "uvm_pkg_uvm_port_base_3556591174087911919_155",
                37326,
                3098,
                26,
                26,
                12884930691,
                "uvm_pkg_uvm_port_base_26085030863532940450_155",
                37326,
                3098,
                26,
                26,
                12884930691,
                "_vcs_unit__657117652_accum_predictor_11_0::uvm_analysis_imp_mon_pred_40370507182949347083_103",
                2812,
                210,
                4,
                4,
                4294974514,
                "_vcs_unit__657117652_accum_scoreboard_11_0",
                13392,
                1245,
                9,
                9,
                4294974544,
                "_vcs_unit__657117652_accum_scoreboard_11_0::uvm_analysis_imp_mon_scbd_18778333493403702609_104",
                2812,
                210,
                4,
                4,
                4294974552,
                "_vcs_unit__657117652_accum_scoreboard_11_0::uvm_analysis_imp_pred_scbd_18778333493403702609_104",
                2812,
                210,
                4,
                4,
                4294974556,
                "uvm_pkg_uvm_sequence_24844159852957008461_78",
                4464,
                217,
                7,
                7,
                12884939419,
                "uvm_pkg_uvm_sequence_27081641443397297811_68",
                4235,
                201,
                7,
                7,
                12884939419,
                "uvm_pkg_uvm_sequence_2437592303813233279_130",
                4767,
                242,
                7,
                7,
                12884939419,
                "_vcs_unit__657117652_accum_base_seq_11_0",
                1147,
                54,
                2,
                2,
                4294974599,
                "_vcs_unit__657117652_accum_first_seq_11_0",
                13151,
                1048,
                17,
                10,
                4294974607,
                "_vcs_unit__657117652_case1_sequence_11_0",
                13287,
                1040,
                19,
                10,
                4294974717,
                "uvm_pkg_uvm_pool_42371590912437262221_40",
                9316,
                538,
                19,
                19,
                12884905182,
                "uvm_pkg_uvm_pool_11098882532832725096_38",
                12029,
                796,
                19,
                19,
                12884905182,
                "uvm_pkg_uvm_pool_42834055751402745537_69",
                12292,
                825,
                19,
                19,
                12884905182,
                "uvm_pkg_uvm_pool_28656355422713151376_11",
                11839,
                821,
                19,
                19,
                12884905182,
                "uvm_pkg_uvm_pool_32071924371089432609_20",
                11886,
                859,
                19,
                19,
                12884905182,
                "uvm_pkg_uvm_pool_9945807051447260144_52",
                12292,
                825,
                19,
                19,
                12884905182,
                "uvm_pkg_uvm_pool_11732178212485972888_36",
                12292,
                825,
                19,
                19,
                12884905182,
                "uvm_pkg_uvm_pool_32868110861242157583_61",
                12292,
                825,
                19,
                19,
                12884905182,
                "uvm_pkg_uvm_pool_2223740478782874312_68",
                9316,
                538,
                19,
                19,
                12884905182,
                "uvm_pkg_uvm_pool_19409840873840241338_85",
                12435,
                833,
                19,
                19,
                12884905182,
                "uvm_pkg_uvm_pool_2293449267561664548_67",
                12075,
                804,
                19,
                19,
                12884905182,
                "uvm_pkg_uvm_pool_35087391001878650323_33",
                12075,
                804,
                19,
                19,
                12884905182,
                "uvm_pkg_uvm_pool_13696848301000834817_33",
                9316,
                538,
                19,
                19,
                12884905182,
                "uvm_pkg_uvm_pool_16650238291282474324_76",
                12292,
                825,
                19,
                19,
                12884905182,
                "uvm_pkg_uvm_pool_19483435901447623860_74",
                9316,
                538,
                19,
                19,
                12884905182,
                "uvm_pkg_uvm_pool_1790989461755815771_33",
                9316,
                538,
                19,
                19,
                12884905182,
                "uvm_pkg_uvm_pool_2668832729852931290_39",
                12292,
                825,
                19,
                19,
                12884905182,
                "uvm_pkg_uvm_object_string_pool_38085949473833222917_33",
                5303,
                310,
                10,
                10,
                12884905395,
                "uvm_pkg_uvm_object_string_pool_29854323192896610176_31",
                6555,
                400,
                10,
                10,
                12884905395,
                "uvm_pkg_uvm_object_string_pool_2759974267363547312_60",
                6554,
                398,
                10,
                10,
                12884905395,
                "uvm_pkg_uvm_object_string_pool_22720307942187480989_26",
                6553,
                398,
                10,
                10,
                12884905395,
                "uvm_pkg_uvm_queue_10131729133184263146_34",
                15968,
                1381,
                18,
                18,
                12884905534,
                "uvm_pkg_uvm_queue_12401831152739582252_34",
                0,
                0,
                0,
                0,
                12884905534,
                "uvm_pkg_uvm_queue_22079939174174364057_39",
                0,
                0,
                0,
                0,
                12884905534,
                "uvm_pkg_uvm_queue_31897947402315526169_41",
                0,
                0,
                0,
                0,
                12884905534,
                "uvm_pkg_uvm_queue_1056094291977123570_7",
                10185,
                719,
                18,
                18,
                12884905534,
                "uvm_pkg_uvm_component_registry_6006117703813170688_115",
                10407,
                771,
                11,
                11,
                12884907517,
                "uvm_pkg_uvm_component_registry_5812522081072586346_105",
                0,
                0,
                0,
                0,
                12884907517,
                "uvm_pkg_uvm_component_registry_28111348063868330604_167",
                0,
                0,
                0,
                0,
                12884907517,
                "uvm_pkg_uvm_component_registry_5474203353199000576_58",
                0,
                0,
                0,
                0,
                12884907517,
                "uvm_pkg_uvm_component_registry_5692230932714981841_52",
                0,
                0,
                0,
                0,
                12884907517,
                "uvm_pkg_uvm_component_registry_30745052132742867287_79",
                0,
                0,
                0,
                0,
                12884907517,
                "uvm_pkg_uvm_component_registry_26868893352653060586_75",
                0,
                0,
                0,
                0,
                12884907517,
                "uvm_pkg_uvm_component_registry_33026817772816557919_58",
                0,
                0,
                0,
                0,
                12884907517,
                "uvm_pkg_uvm_component_registry_22091576082676059373_60",
                0,
                0,
                0,
                0,
                12884907517,
                "uvm_pkg_uvm_component_registry_6530464093745080437_71",
                0,
                0,
                0,
                0,
                12884907517,
                "uvm_pkg_uvm_component_registry_4319512103314391777_71",
                0,
                0,
                0,
                0,
                12884907517,
                "uvm_pkg_uvm_component_registry_23060480431330782246_69",
                0,
                0,
                0,
                0,
                12884907517,
                "uvm_pkg_uvm_object_registry_4935053363517778086_51",
                10560,
                792,
                11,
                11,
                12884907648,
                "uvm_pkg_uvm_object_registry_33331550721853239193_53",
                0,
                0,
                0,
                0,
                12884907648,
                "uvm_pkg_uvm_object_registry_1906819324266042653_63",
                0,
                0,
                0,
                0,
                12884907648,
                "uvm_pkg_uvm_object_registry_27138642393390246789_61",
                0,
                0,
                0,
                0,
                12884907648,
                "uvm_pkg_uvm_object_registry_29344154181922724425_75",
                0,
                0,
                0,
                0,
                12884907648,
                "uvm_pkg_uvm_object_registry_28767600201035024889_53",
                0,
                0,
                0,
                0,
                12884907648,
                "uvm_pkg_uvm_object_registry_2164067094159664132_61",
                0,
                0,
                0,
                0,
                12884907648,
                "uvm_pkg_uvm_object_registry_1347888261580838246_53",
                0,
                0,
                0,
                0,
                12884907648,
                "uvm_pkg_uvm_object_registry_30483053094059138737_73",
                0,
                0,
                0,
                0,
                12884907648,
                "uvm_pkg_uvm_object_registry_14439487293049952778_53",
                0,
                0,
                0,
                0,
                12884907648,
                "uvm_pkg_uvm_object_registry_13870511283927333234_55",
                0,
                0,
                0,
                0,
                12884907648,
                "uvm_pkg_uvm_object_registry_1803450658736655051_140",
                7088,
                507,
                11,
                11,
                12884907648,
                "uvm_pkg_uvm_object_registry_20195001883255690309_51",
                0,
                0,
                0,
                0,
                12884907648,
                "uvm_pkg_uvm_object_registry_1837333109238589200_49",
                0,
                0,
                0,
                0,
                12884907648,
                "uvm_pkg_uvm_object_registry_6547918343632128737_65",
                0,
                0,
                0,
                0,
                12884907648,
                "uvm_pkg_uvm_object_registry_4364088662927209418_59",
                0,
                0,
                0,
                0,
                12884907648,
                "uvm_pkg_uvm_object_registry_14191343452413913236_69",
                0,
                0,
                0,
                0,
                12884907648,
                "uvm_pkg_uvm_object_registry_342307119856880728_71",
                0,
                0,
                0,
                0,
                12884907648,
                "uvm_pkg_uvm_object_registry_12899728703437824960_130",
                7088,
                507,
                11,
                11,
                12884907648,
                "uvm_pkg_uvm_object_registry_27002261902274500827_55",
                0,
                0,
                0,
                0,
                12884907648,
                "uvm_pkg_uvm_object_registry_5609186164052521641_69",
                0,
                0,
                0,
                0,
                12884907648,
                "uvm_pkg_uvm_object_registry_15399770231763244496_55",
                0,
                0,
                0,
                0,
                12884907648,
                "uvm_pkg_uvm_object_registry_273851227787825907_61",
                0,
                0,
                0,
                0,
                12884907648,
                "uvm_pkg_uvm_object_registry_1116471086386374402_47",
                0,
                0,
                0,
                0,
                12884907648,
                "uvm_pkg_uvm_object_registry_17692521782985197028_65",
                0,
                0,
                0,
                0,
                12884907648,
                "uvm_pkg_uvm_object_registry_38910011271399345106_51",
                0,
                0,
                0,
                0,
                12884907648,
                "uvm_pkg_uvm_object_registry_37873060981902812299_65",
                0,
                0,
                0,
                0,
                12884907648,
                "uvm_pkg_uvm_object_registry_433731176719709738_51",
                0,
                0,
                0,
                0,
                12884907648,
                "uvm_pkg_uvm_object_registry_38280531571839998128_59",
                0,
                0,
                0,
                0,
                12884907648,
                "uvm_pkg_uvm_object_registry_1348953888709792696_65",
                0,
                0,
                0,
                0,
                12884907648,
                "uvm_pkg_uvm_object_registry_36353121283939136215_65",
                0,
                0,
                0,
                0,
                12884907648,
                "uvm_pkg_uvm_object_registry_14423394572653327039_73",
                0,
                0,
                0,
                0,
                12884907648,
                "uvm_pkg_uvm_object_registry_13218283181657985668_63",
                0,
                0,
                0,
                0,
                12884907648,
                "uvm_pkg_uvm_object_registry_28828704562697250440_65",
                0,
                0,
                0,
                0,
                12884907648,
                "uvm_pkg_uvm_object_registry_31367509471821760984_73",
                0,
                0,
                0,
                0,
                12884907648,
                "uvm_pkg_uvm_object_registry_2120333925708090850_59",
                0,
                0,
                0,
                0,
                12884907648,
                "uvm_pkg_uvm_object_registry_35167551683033718112_87",
                0,
                0,
                0,
                0,
                12884907648,
                "uvm_pkg_uvm_object_registry_28596261891528940983_58",
                0,
                0,
                0,
                0,
                12884907648,
                "uvm_pkg_uvm_object_registry_3895700948830924767_56",
                0,
                0,
                0,
                0,
                12884907648,
                "uvm_pkg_uvm_spell_chkr_29865849301974608402_58",
                9017,
                1000,
                6,
                6,
                12884907865,
                "uvm_pkg_m_uvm_resource_converter_27000910942830678221_40",
                1767,
                102,
                5,
                5,
                12884909793,
                "uvm_pkg_m_uvm_resource_converter_25863622094079981516_23",
                1226,
                70,
                3,
                3,
                12884909793,
                "uvm_pkg_m_uvm_resource_converter_1056094291977123570_7",
                1241,
                70,
                3,
                3,
                12884909793,
                "uvm_pkg_m_uvm_resource_converter_17002614941379949671_32",
                0,
                0,
                0,
                0,
                12884909793,
                "uvm_pkg_m_uvm_resource_converter_3733140680830918994_39",
                0,
                0,
                0,
                0,
                12884909793,
                "uvm_pkg_m_uvm_resource_converter_40194292771222167562_12",
                1203,
                70,
                3,
                3,
                12884909793,
                "uvm_pkg_m_uvm_resource_converter_20178826502325633761_4",
                1203,
                70,
                3,
                3,
                12884909793,
                "uvm_pkg_m_uvm_resource_converter_27061203961639428043_15",
                1203,
                70,
                3,
                3,
                12884909793,
                "uvm_pkg_m_uvm_resource_converter_40973394903465487470_45",
                1200,
                70,
                3,
                3,
                12884909793,
                "uvm_pkg_m_uvm_resource_converter_2720976050237557357_47",
                0,
                0,
                0,
                0,
                12884909793,
                "uvm_pkg_m_uvm_resource_converter_30894295071101572826_35",
                0,
                0,
                0,
                0,
                12884909793,
                "uvm_pkg_m_uvm_resource_converter_11265387052000028149_4",
                1200,
                70,
                3,
                3,
                12884909793,
                "uvm_pkg_m_uvm_resource_converter_24042704503083235035_9",
                1203,
                70,
                3,
                3,
                12884909793,
                "uvm_pkg_m_uvm_resource_converter_13497450083373860521_8",
                1211,
                71,
                3,
                3,
                12884909793,
                "uvm_pkg_m_uvm_resource_converter_31322854743492999953_5",
                1203,
                70,
                3,
                3,
                12884909793,
                "uvm_pkg_m_uvm_resource_converter_2512634884385210231_6",
                1200,
                70,
                3,
                3,
                12884909793,
                "uvm_pkg_m_uvm_resource_converter_34992156034188263183_4",
                1200,
                70,
                3,
                3,
                12884909793,
                "uvm_pkg_m_uvm_resource_converter_9662999622205632575_8",
                1211,
                73,
                3,
                3,
                12884909793,
                "uvm_pkg_m_uvm_resource_converter_36366895843937153226_5",
                1239,
                77,
                3,
                3,
                12884909793,
                "uvm_pkg_m_uvm_resource_converter_42308963162334584268_5",
                1206,
                70,
                3,
                3,
                12884909793,
                "uvm_pkg_m_uvm_resource_converter_14687473452946514378_11",
                1203,
                70,
                3,
                3,
                12884909793,
                "uvm_pkg_m_uvm_resource_converter_41811330383157291703_12",
                1203,
                70,
                3,
                3,
                12884909793,
                "uvm_pkg_m_uvm_resource_converter_20090769462820574014_10",
                1347,
                70,
                3,
                3,
                12884909793,
                "uvm_pkg_uvm_resource_27000910942830678221_40",
                18773,
                1529,
                17,
                17,
                12884909447,
                "uvm_pkg_uvm_resource_25863622094079981516_23",
                15091,
                1151,
                17,
                17,
                12884909447,
                "uvm_pkg_uvm_resource_1056094291977123570_7",
                15100,
                1155,
                17,
                17,
                12884909447,
                "uvm_pkg_uvm_resource_17002614941379949671_32",
                0,
                0,
                0,
                0,
                12884909447,
                "uvm_pkg_uvm_resource_3733140680830918994_39",
                0,
                0,
                0,
                0,
                12884909447,
                "uvm_pkg_uvm_resource_40194292771222167562_12",
                11462,
                746,
                17,
                17,
                12884909447,
                "uvm_pkg_uvm_resource_20178826502325633761_4",
                13629,
                1011,
                17,
                17,
                12884909447,
                "uvm_pkg_uvm_resource_27061203961639428043_15",
                11405,
                709,
                17,
                17,
                12884909447,
                "uvm_pkg_uvm_resource_40973394903465487470_45",
                13491,
                969,
                17,
                17,
                12884909447,
                "uvm_pkg_uvm_resource_2720976050237557357_47",
                0,
                0,
                0,
                0,
                12884909447,
                "uvm_pkg_uvm_resource_30894295071101572826_35",
                0,
                0,
                0,
                0,
                12884909447,
                "uvm_pkg_uvm_resource_11265387052000028149_4",
                14889,
                1144,
                17,
                17,
                12884909447,
                "uvm_pkg_uvm_resource_24042704503083235035_9",
                11467,
                747,
                17,
                17,
                12884909447,
                "uvm_pkg_uvm_resource_13497450083373860521_8",
                11484,
                749,
                17,
                17,
                12884909447,
                "uvm_pkg_uvm_resource_31322854743492999953_5",
                11467,
                747,
                17,
                17,
                12884909447,
                "uvm_pkg_uvm_resource_2512634884385210231_6",
                11452,
                746,
                17,
                17,
                12884909447,
                "uvm_pkg_uvm_resource_34992156034188263183_4",
                11452,
                746,
                17,
                17,
                12884909447,
                "uvm_pkg_uvm_resource_9662999622205632575_8",
                11485,
                754,
                17,
                17,
                12884909447,
                "uvm_pkg_uvm_resource_36366895843937153226_5",
                11548,
                759,
                17,
                17,
                12884909447,
                "uvm_pkg_uvm_resource_42308963162334584268_5",
                11476,
                746,
                17,
                17,
                12884909447,
                "uvm_pkg_uvm_resource_14687473452946514378_11",
                11467,
                747,
                17,
                17,
                12884909447,
                "uvm_pkg_uvm_resource_41811330383157291703_12",
                11467,
                747,
                17,
                17,
                12884909447,
                "uvm_pkg_uvm_resource_20090769462820574014_10",
                14751,
                1122,
                17,
                17,
                12884909447,
                "uvm_pkg_m_uvm_resource_default_converter_24042704503083235035_9",
                3167,
                250,
                4,
                4,
                12884909817,
                "uvm_pkg_m_uvm_resource_default_converter_20178826502325633761_4",
                3162,
                249,
                4,
                4,
                12884909817,
                "uvm_pkg_m_uvm_resource_default_converter_13497450083373860521_8",
                3170,
                252,
                4,
                4,
                12884909817,
                "uvm_pkg_m_uvm_resource_default_converter_31322854743492999953_5",
                3167,
                250,
                4,
                4,
                12884909817,
                "uvm_pkg_m_uvm_resource_default_converter_11265387052000028149_4",
                3147,
                249,
                4,
                4,
                12884909817,
                "uvm_pkg_m_uvm_resource_default_converter_2512634884385210231_6",
                3147,
                249,
                4,
                4,
                12884909817,
                "uvm_pkg_m_uvm_resource_default_converter_34992156034188263183_4",
                3147,
                249,
                4,
                4,
                12884909817,
                "uvm_pkg_m_uvm_resource_default_converter_9662999622205632575_8",
                3184,
                254,
                4,
                4,
                12884909817,
                "uvm_pkg_m_uvm_resource_default_converter_36366895843937153226_5",
                3205,
                255,
                4,
                4,
                12884909817,
                "uvm_pkg_m_uvm_resource_default_converter_42308963162334584268_5",
                3168,
                249,
                4,
                4,
                12884909817,
                "uvm_pkg_m_uvm_resource_default_converter_1056094291977123570_7",
                3221,
                250,
                4,
                4,
                12884909817,
                "uvm_pkg_m_uvm_resource_default_converter_25863622094079981516_23",
                3196,
                248,
                4,
                4,
                12884909817,
                "uvm_pkg_m_uvm_resource_default_converter_14687473452946514378_11",
                3167,
                250,
                4,
                4,
                12884909817,
                "uvm_pkg_m_uvm_resource_default_converter_41811330383157291703_12",
                3167,
                250,
                4,
                4,
                12884909817,
                "uvm_pkg_m_uvm_resource_default_converter_40194292771222167562_12",
                3162,
                249,
                4,
                4,
                12884909817,
                "uvm_pkg_uvm_int_rsrc_11_0",
                3094,
                156,
                5,
                5,
                12884910034,
                "uvm_pkg_uvm_string_rsrc_11_0",
                2958,
                133,
                5,
                5,
                12884910057,
                "uvm_pkg_uvm_obj_rsrc_11_0",
                2194,
                95,
                4,
                4,
                12884910078,
                "uvm_pkg_uvm_resource_db_27000910942830678221_40",
                22340,
                1361,
                18,
                18,
                12884910192,
                "uvm_pkg_uvm_resource_db_25863622094079981516_23",
                12261,
                594,
                16,
                16,
                12884910192,
                "uvm_pkg_uvm_resource_db_1056094291977123570_7",
                12329,
                600,
                16,
                16,
                12884910192,
                "uvm_pkg_uvm_resource_db_17002614941379949671_32",
                0,
                0,
                0,
                0,
                12884910192,
                "uvm_pkg_uvm_resource_db_3733140680830918994_39",
                0,
                0,
                0,
                0,
                12884910192,
                "uvm_pkg_uvm_resource_db_40194292771222167562_12",
                9531,
                400,
                16,
                16,
                12884910192,
                "uvm_pkg_uvm_resource_db_11265387052000028149_4",
                12252,
                607,
                16,
                16,
                12884910192,
                "uvm_pkg_uvm_resource_db_20178826502325633761_4",
                12108,
                594,
                16,
                16,
                12884910192,
                "uvm_pkg_uvm_resource_db_2720976050237557357_47",
                0,
                0,
                0,
                0,
                12884910192,
                "uvm_pkg_uvm_resource_db_40973394903465487470_45",
                12024,
                594,
                16,
                16,
                12884910192,
                "uvm_pkg_uvm_resource_db_30894295071101572826_35",
                0,
                0,
                0,
                0,
                12884910192,
                "uvm_pkg_uvm_resource_db_20090769462820574014_10",
                12076,
                594,
                16,
                16,
                12884910192,
                "uvm_pkg_uvm_config_db_27000910942830678221_40",
                13454,
                1094,
                6,
                6,
                12884910607,
                "uvm_pkg_uvm_config_db_25863622094079981516_23",
                12607,
                992,
                6,
                6,
                12884910607,
                "uvm_pkg_uvm_config_db_1056094291977123570_7",
                12571,
                991,
                6,
                6,
                12884910607,
                "uvm_pkg_uvm_config_db_17002614941379949671_32",
                9959,
                773,
                6,
                6,
                12884910607,
                "uvm_pkg_uvm_config_db_3733140680830918994_39",
                6887,
                493,
                6,
                6,
                12884910607,
                "uvm_pkg_uvm_config_db_20178826502325633761_4",
                5874,
                393,
                6,
                6,
                12884910607,
                "uvm_pkg_uvm_config_db_2720976050237557357_47",
                9959,
                773,
                6,
                6,
                12884910607,
                "uvm_pkg_uvm_config_db_40973394903465487470_45",
                5861,
                393,
                6,
                6,
                12884910607,
                "uvm_pkg_uvm_config_db_11265387052000028149_4",
                5861,
                393,
                6,
                6,
                12884910607,
                "uvm_pkg_uvm_config_db_20090769462820574014_10",
                12534,
                995,
                6,
                6,
                12884910607,
                "uvm_pkg_uvm_typeid_12401831152739582252_34",
                2038,
                159,
                3,
                3,
                12884914559,
                "uvm_pkg_uvm_typeid_26457283571261833951_39",
                0,
                0,
                0,
                0,
                12884914559,
                "uvm_pkg_uvm_typeid_3011313423768043667_40",
                0,
                0,
                0,
                0,
                12884914559,
                "uvm_pkg_uvm_typeid_9836671432282947766_35",
                0,
                0,
                0,
                0,
                12884914559,
                "uvm_pkg_uvm_typeid_1084049419402313263_44",
                0,
                0,
                0,
                0,
                12884914559,
                "uvm_pkg_uvm_typeid_31019486001803716048_45",
                0,
                0,
                0,
                0,
                12884914559,
                "uvm_pkg_uvm_typeid_11704699723925447941_44",
                0,
                0,
                0,
                0,
                12884914559,
                "uvm_pkg_uvm_typeid_34134683632350250451_29",
                0,
                0,
                0,
                0,
                12884914559,
                "uvm_pkg_uvm_typeid_3401845221661803279_33",
                0,
                0,
                0,
                0,
                12884914559,
                "uvm_pkg_uvm_typeid_7929638273969762994_38",
                0,
                0,
                0,
                0,
                12884914559,
                "uvm_pkg_uvm_typeid_36840009753431794161_29",
                0,
                0,
                0,
                0,
                12884914559,
                "uvm_pkg_uvm_typeid_3836623090295522255_35",
                0,
                0,
                0,
                0,
                12884914559,
                "uvm_pkg_uvm_typeid_33180307611796608036_36",
                0,
                0,
                0,
                0,
                12884914559,
                "uvm_pkg_uvm_typeid_12470599392681938761_40",
                0,
                0,
                0,
                0,
                12884914559,
                "uvm_pkg_uvm_typeid_28427035364151357801_30",
                0,
                0,
                0,
                0,
                12884914559,
                "uvm_pkg_uvm_typeid_19044983891253896198_34",
                0,
                0,
                0,
                0,
                12884914559,
                "uvm_pkg_uvm_typed_callbacks_26457283571261833951_39",
                33812,
                3126,
                10,
                10,
                12884914673,
                "uvm_pkg_uvm_typed_callbacks_9836671432282947766_35",
                0,
                0,
                0,
                0,
                12884914673,
                "uvm_pkg_uvm_typed_callbacks_31019486001803716048_45",
                0,
                0,
                0,
                0,
                12884914673,
                "uvm_pkg_uvm_typed_callbacks_34134683632350250451_29",
                0,
                0,
                0,
                0,
                12884914673,
                "uvm_pkg_uvm_typed_callbacks_7929638273969762994_38",
                0,
                0,
                0,
                0,
                12884914673,
                "uvm_pkg_uvm_typed_callbacks_36840009753431794161_29",
                0,
                0,
                0,
                0,
                12884914673,
                "uvm_pkg_uvm_typed_callbacks_3836623090295522255_35",
                0,
                0,
                0,
                0,
                12884914673,
                "uvm_pkg_uvm_typed_callbacks_33180307611796608036_36",
                0,
                0,
                0,
                0,
                12884914673,
                "uvm_pkg_uvm_typed_callbacks_28427035364151357801_30",
                0,
                0,
                0,
                0,
                12884914673,
                "uvm_pkg_uvm_callbacks_798380094140731869_79",
                45046,
                4081,
                17,
                17,
                12884914962,
                "uvm_pkg_uvm_callbacks_3760896427231740967_73",
                0,
                0,
                0,
                0,
                12884914962,
                "uvm_pkg_uvm_callbacks_29816384132329754774_79",
                0,
                0,
                0,
                0,
                12884914962,
                "uvm_pkg_uvm_callbacks_4125919662173130704_69",
                0,
                0,
                0,
                0,
                12884914962,
                "uvm_pkg_uvm_callbacks_4160137027374880434_89",
                0,
                0,
                0,
                0,
                12884914962,
                "uvm_pkg_uvm_callbacks_30559174163891993319_79",
                0,
                0,
                0,
                0,
                12884914962,
                "uvm_pkg_uvm_callbacks_19226769593172006443_62",
                0,
                0,
                0,
                0,
                12884914962,
                "uvm_pkg_uvm_callbacks_2406280077311694533_63",
                0,
                0,
                0,
                0,
                12884914962,
                "uvm_pkg_uvm_callbacks_25874056332755742618_71",
                0,
                0,
                0,
                0,
                12884914962,
                "uvm_pkg_uvm_callbacks_3453533772665706993_72",
                0,
                0,
                0,
                0,
                12884914962,
                "uvm_pkg_uvm_callbacks_16157689474253550089_62",
                0,
                0,
                0,
                0,
                12884914962,
                "uvm_pkg_uvm_callbacks_5019175871376577767_63",
                0,
                0,
                0,
                0,
                12884914962,
                "uvm_pkg_uvm_callbacks_19000355451864305105_68",
                0,
                0,
                0,
                0,
                12884914962,
                "uvm_pkg_uvm_callbacks_1537919828403250345_69",
                0,
                0,
                0,
                0,
                12884914962,
                "uvm_pkg_uvm_callbacks_8485508411680905163_76",
                0,
                0,
                0,
                0,
                12884914962,
                "uvm_pkg_uvm_callbacks_28796025763716974123_70",
                0,
                0,
                0,
                0,
                12884914962,
                "uvm_pkg_uvm_callbacks_5292868251138386083_64",
                0,
                0,
                0,
                0,
                12884914962,
                "uvm_pkg_uvm_callbacks_6692293671863204093_64",
                0,
                0,
                0,
                0,
                12884914962,
                "uvm_pkg_uvm_callbacks_40711032602292020929_89",
                0,
                0,
                0,
                0,
                12884914962,
                "uvm_pkg_uvm_callback_iter_798380094140731869_79",
                6301,
                536,
                9,
                9,
                12884915538,
                "uvm_pkg_uvm_callback_iter_19226769593172006443_62",
                0,
                0,
                0,
                0,
                12884915538,
                "uvm_pkg_uvm_callback_iter_25874056332755742618_71",
                0,
                0,
                0,
                0,
                12884915538,
                "uvm_pkg_uvm_callback_iter_16157689474253550089_62",
                0,
                0,
                0,
                0,
                12884915538,
                "uvm_pkg_uvm_callback_iter_19000355451864305105_68",
                0,
                0,
                0,
                0,
                12884915538,
                "uvm_pkg_uvm_callback_iter_8485508411680905163_76",
                0,
                0,
                0,
                0,
                12884915538,
                "uvm_pkg_uvm_callback_iter_5292868251138386083_64",
                0,
                0,
                0,
                0,
                12884915538,
                "uvm_pkg_uvm_callback_iter_40711032602292020929_89",
                0,
                0,
                0,
                0,
                12884915538,
                "uvm_pkg_uvm_tlm_if_base_24844159852957008461_78",
                6564,
                300,
                14,
                14,
                12884930106,
                "uvm_pkg_uvm_tlm_if_base_27081641443397297811_68",
                6564,
                300,
                14,
                14,
                12884930106,
                "uvm_pkg_uvm_tlm_if_base_2437592303813233279_130",
                6564,
                300,
                14,
                14,
                12884930106,
                "uvm_pkg_uvm_sqr_if_base_24844159852957008461_78",
                4888,
                217,
                11,
                11,
                12884930316,
                "uvm_pkg_uvm_sqr_if_base_27081641443397297811_68",
                4884,
                217,
                11,
                11,
                12884930316,
                "uvm_pkg_uvm_sqr_if_base_2437592303813233279_130",
                4886,
                219,
                11,
                11,
                12884930316,
                "uvm_pkg_uvm_port_component_34533239451891830907_126",
                5496,
                374,
                10,
                10,
                12884930604,
                "uvm_pkg_uvm_port_component_23145110241044876076_126",
                5496,
                374,
                10,
                10,
                12884930604,
                "uvm_pkg_uvm_port_component_2311547681826351055_116",
                5496,
                374,
                10,
                10,
                12884930604,
                "uvm_pkg_uvm_port_component_234753672576675992_116",
                5496,
                374,
                10,
                10,
                12884930604,
                "uvm_pkg_uvm_port_component_31105166362190498725_178",
                5496,
                374,
                10,
                10,
                12884930604,
                "uvm_pkg_uvm_port_component_9258116793423919346_178",
                5496,
                374,
                10,
                10,
                12884930604,
                "uvm_pkg_uvm_put_imp_3520587431117154525_105",
                3431,
                235,
                6,
                6,
                12884931757,
                "uvm_pkg_uvm_put_imp_14494172543974948263_95",
                3431,
                235,
                6,
                6,
                12884931757,
                "uvm_pkg_uvm_put_imp_23564023774228628447_157",
                3431,
                235,
                6,
                6,
                12884931757,
                "uvm_pkg_uvm_get_peek_imp_3520587431117154525_105",
                4780,
                302,
                9,
                9,
                12884931811,
                "uvm_pkg_uvm_get_peek_imp_14494172543974948263_95",
                4780,
                302,
                9,
                9,
                12884931811,
                "uvm_pkg_uvm_get_peek_imp_23564023774228628447_157",
                4780,
                302,
                9,
                9,
                12884931811,
                "uvm_pkg_uvm_analysis_port_11784808032147832686_39",
                3342,
                236,
                4,
                4,
                12884932564,
                "uvm_pkg_uvm_analysis_port_36951920133088784204_34",
                3342,
                236,
                4,
                4,
                12884932564,
                "uvm_pkg_uvm_analysis_port_42816961243213493938_65",
                3342,
                236,
                4,
                4,
                12884932564,
                "uvm_pkg_uvm_analysis_imp_32194365862697004679_115",
                2803,
                210,
                4,
                4,
                12884932627,
                "uvm_pkg_uvm_analysis_imp_12888305263488070193_105",
                2803,
                210,
                4,
                4,
                12884932627,
                "uvm_pkg_uvm_analysis_imp_8868730701715149314_167",
                2803,
                210,
                4,
                4,
                12884932627,
                "uvm_pkg_uvm_analysis_export_11784808032147832686_39",
                3342,
                236,
                4,
                4,
                12884932649,
                "uvm_pkg_uvm_analysis_export_36951920133088784204_34",
                3342,
                236,
                4,
                4,
                12884932649,
                "uvm_pkg_uvm_analysis_export_42816961243213493938_65",
                3342,
                236,
                4,
                4,
                12884932649,
                "uvm_pkg_uvm_tlm_fifo_base_11784808032147832686_39",
                13767,
                1262,
                20,
                20,
                12884932737,
                "uvm_pkg_uvm_tlm_fifo_base_36951920133088784204_34",
                13768,
                1264,
                20,
                20,
                12884932737,
                "uvm_pkg_uvm_tlm_fifo_base_42816961243213493938_65",
                13768,
                1264,
                20,
                20,
                12884932737,
                "uvm_pkg_uvm_tlm_fifo_11784808032147832686_39",
                9068,
                575,
                18,
                18,
                12884932990,
                "uvm_pkg_uvm_tlm_fifo_36951920133088784204_34",
                10197,
                708,
                20,
                18,
                12884932990,
                "uvm_pkg_uvm_tlm_fifo_42816961243213493938_65",
                10197,
                708,
                20,
                18,
                12884932990,
                "uvm_pkg_uvm_seq_item_pull_port_24844159852957008461_78",
                5444,
                246,
                12,
                12,
                12884933580,
                "uvm_pkg_uvm_seq_item_pull_port_2437592303813233279_130",
                6466,
                365,
                13,
                12,
                12884933580,
                "uvm_pkg_uvm_seq_item_pull_imp_27764548292519292536_179",
                6209,
                353,
                12,
                12,
                12884933615,
                "uvm_pkg_uvm_seq_item_pull_imp_26815678913984971942_159",
                6420,
                366,
                12,
                12,
                12884933615,
                "uvm_pkg_uvm_seq_item_pull_imp_26780651454174558798_283",
                6930,
                434,
                13,
                12,
                12884933615,
                "uvm_pkg_uvm_sequencer_analysis_fifo_11784808032147832686_39",
                2645,
                188,
                3,
                3,
                12884937325,
                "uvm_pkg_uvm_sequencer_analysis_fifo_36951920133088784204_34",
                2645,
                188,
                3,
                3,
                12884937325,
                "uvm_pkg_uvm_sequencer_analysis_fifo_42816961243213493938_65",
                2645,
                188,
                3,
                3,
                12884937325,
                "uvm_pkg_uvm_random_sequence_11_0",
                12670,
                1030,
                16,
                13,
                12884940404,
                "uvm_pkg_uvm_exhaustive_sequence_11_0",
                11001,
                879,
                15,
                12,
                12884940517,
                "uvm_pkg_uvm_simple_sequence_11_0",
                9259,
                755,
                15,
                8,
                12884940623,
                "uvm_pkg_uvm_reg_sequence_30395111473839290680_100",
                21285,
                1427,
                34,
                20,
                12884944739,
                "uvm_pkg_uvm_reg_sequence_15155903533960952999_90",
                21285,
                1427,
                34,
                20,
                12884944739,
                "uvm_pkg_uvm_reg_frontdoor_11_0",
                892,
                41,
                2,
                2,
                12884945198,
                "uvm_pkg_uvm_reg_indirect_ftdr_seq_11_0",
                1383,
                64,
                3,
                3,
                12884952608,
                "uvm_pkg_uvm_reg_hw_reset_seq_11_0",
                20052,
                1719,
                12,
                12,
                12884963306,
                "uvm_pkg_uvm_reg_single_bit_bash_seq_11_0",
                22804,
                2066,
                11,
                11,
                12884963516,
                "uvm_pkg_uvm_reg_bit_bash_seq_11_0",
                17516,
                1356,
                23,
                12,
                12884963671,
                "uvm_pkg_uvm_mem_single_walk_seq_11_0",
                24275,
                2508,
                10,
                10,
                12884963833,
                "uvm_pkg_uvm_mem_walk_seq_11_0",
                19070,
                1513,
                23,
                12,
                12884963970,
                "uvm_pkg_uvm_mem_single_access_seq_11_0",
                27594,
                2626,
                20,
                10,
                12884964125,
                "uvm_pkg_uvm_mem_access_seq_11_0",
                21440,
                1800,
                23,
                12,
                12884964270,
                "uvm_pkg_uvm_reg_single_access_seq_11_0",
                25758,
                2216,
                17,
                10,
                12884964447,
                "uvm_pkg_uvm_reg_access_seq_11_0",
                19925,
                1645,
                23,
                12,
                12884964599,
                "uvm_pkg_uvm_reg_mem_access_seq_11_0",
                13665,
                1019,
                18,
                11,
                12884964722,
                "uvm_pkg_uvm_reg_shared_access_seq_11_0",
                25197,
                2561,
                10,
                10,
                12884964829,
                "uvm_pkg_uvm_mem_shared_access_seq_11_0",
                25748,
                2476,
                10,
                10,
                12884964978,
                "uvm_pkg_uvm_reg_mem_shared_access_seq_11_0",
                26420,
                2227,
                27,
                12,
                12884965126,
                "uvm_pkg_uvm_reg_mem_built_in_seq_11_0",
                32478,
                2745,
                33,
                10,
                12884965291,
                "uvm_pkg_uvm_reg_mem_hdl_paths_seq_11_0",
                49361,
                4954,
                14,
                14,
                12884965449
            ],
            "child_modules": {},
            "Compiled Times": 1,
            "Compiled": "Yes",
            "end_perf": [
                4.7568669319152832,
                4.3684209999999997,
                0.25579000000000002,
                349244,
                349244,
                304741165174857,
                42949672961,
                0
            ],
            "nMops": 154053,
            "nQuads": 48241,
            "nRouts": 2733
        },
        "std": {
            "start_perf": [
                4.7979071140289307,
                4.4047159999999996,
                0.26003500000000002,
                349244,
                349244,
                1658908886.4297781,
                304741283881659
            ],
            "svclass": [
                "$vcs_nba_dyn_obj",
                576,
                35,
                2,
                2,
                0,
                "sigprop$$",
                576,
                35,
                2,
                2,
                0,
                "process",
                2378,
                200,
                8,
                8,
                0,
                "event",
                597,
                34,
                2,
                2,
                0,
                "mailbox",
                1769,
                140,
                9,
                9,
                0,
                "semaphore",
                1128,
                84,
                5,
                5,
                0
            ],
            "child_modules": {},
            "Compiled Times": 1,
            "Compiled": "Yes",
            "end_perf": [
                4.8039560317993164,
                4.4107630000000002,
                0.26003500000000002,
                349244,
                349244,
                304741301465432,
                8589934594,
                0
            ],
            "nMops": 543,
            "nQuads": 224,
            "nRouts": 34
        },
        "uvm_pkg": {
            "start_perf": [
                4.8040130138397217,
                4.4108219999999996,
                0.26003500000000002,
                349244,
                349244,
                1658908886.435884,
                304741301548517
            ],
            "svclass": [
                "_vcs_struct_uvm_hdl_path_slice",
                0,
                0,
                0,
                0,
                0,
                "_vcs_struct_m_verbosity_setting",
                0,
                0,
                0,
                0,
                0,
                "_vcs_struct_uvm_printer_row_info",
                0,
                0,
                0,
                0,
                0,
                "_vcs_struct_Blasted_access_t",
                0,
                0,
                0,
                0,
                0,
                "_vcs_struct_access_t",
                0,
                0,
                0,
                0,
                0,
                "uvm_cmdline_processor",
                21793,
                2222,
                12,
                12,
                12884929644,
                "uvm_printer",
                30244,
                2856,
                20,
                20,
                12884910996,
                "uvm_table_printer",
                12988,
                1453,
                4,
                4,
                12884911213,
                "uvm_tree_printer",
                9163,
                1103,
                3,
                3,
                12884911262,
                "uvm_line_printer",
                1330,
                116,
                2,
                2,
                12884911294,
                "uvm_comparer",
                24676,
                2654,
                11,
                11,
                12884912126,
                "uvm_packer",
                24451,
                2793,
                31,
                31,
                12884912551,
                "uvm_recorder",
                24254,
                2224,
                24,
                24,
                12884913339,
                "uvm_void",
                763,
                41,
                2,
                2,
                12884903054,
                "uvm_object",
                52033,
                4434,
                41,
                41,
                12884903850,
                "uvm_scope_stack",
                10351,
                1072,
                13,
                13,
                12884903069,
                "uvm_status_container",
                6810,
                707,
                6,
                6,
                12884903212,
                "uvm_copy_map",
                3345,
                201,
                6,
                6,
                12884903327,
                "uvm_component",
                175117,
                14856,
                149,
                122,
                12884922532,
                "uvm_root",
                75790,
                6932,
                41,
                26,
                12884924228,
                "uvm_report_object",
                23833,
                1524,
                39,
                39,
                12884917751,
                "uvm_object_wrapper",
                2497,
                146,
                6,
                6,
                12884906394,
                "uvm_objection",
                80121,
                7860,
                68,
                35,
                12884927359,
                "uvm_barrier",
                11358,
                1073,
                15,
                15,
                12884914219,
                "uvm_event",
                20015,
                1900,
                30,
                24,
                12884913854,
                "uvm_factory_override",
                2822,
                306,
                2,
                2,
                12884906437,
                "uvm_factory_queue_class",
                763,
                41,
                2,
                2,
                12884905736,
                "uvm_factory",
                105742,
                10814,
                23,
                23,
                12884905808,
                "uvm_resource_base",
                15480,
                1218,
                19,
                19,
                12884908233,
                "uvm_resource_types",
                668,
                36,
                2,
                2,
                12884908145,
                "uvm_resource_options",
                2268,
                160,
                6,
                6,
                12884908192,
                "get_t",
                763,
                41,
                2,
                2,
                12884908634,
                "uvm_resource_pool",
                44931,
                4026,
                27,
                27,
                12884908702,
                "m_uvm_resource_default_converters",
                3998,
                295,
                4,
                4,
                12884909923,
                "uvm_resource_db_options",
                3570,
                278,
                6,
                6,
                12884910487,
                "uvm_phase",
                157813,
                14327,
                204,
                57,
                12884919149,
                "m_uvm_waiter",
                1301,
                91,
                2,
                2,
                12884910581,
                "uvm_config_db_options",
                3570,
                278,
                6,
                6,
                12884910861,
                "uvm_printer_knobs",
                6246,
                1010,
                3,
                3,
                12884911320,
                "uvm_event_callback",
                2510,
                111,
                5,
                5,
                12884913767,
                "uvm_callback",
                4703,
                436,
                7,
                7,
                12884915641,
                "uvm_callbacks_base",
                9688,
                844,
                11,
                11,
                12884914585,
                "uvm_typeid_base",
                763,
                41,
                2,
                2,
                12884914545,
                "uvm_report_handler",
                32018,
                2491,
                29,
                29,
                12884917048,
                "uvm_report_server",
                33250,
                2877,
                29,
                29,
                12884916429,
                "uvm_report_catcher",
                32872,
                3186,
                32,
                32,
                12884915812,
                "sev_id_struct",
                673,
                36,
                2,
                2,
                12884915738,
                "uvm_report_global_server",
                1827,
                85,
                4,
                4,
                12884916963,
                "uvm_env",
                2070,
                135,
                4,
                4,
                12884935006,
                "uvm_transaction",
                28877,
                3153,
                26,
                26,
                12884918353,
                "uvm_test_done_objection",
                25937,
                2113,
                57,
                15,
                12884928418,
                "uvm_sequencer_base",
                120502,
                12995,
                123,
                55,
                12884935682,
                "uvm_domain",
                19827,
                2008,
                9,
                9,
                12884920991,
                "uvm_task_phase",
                10950,
                971,
                11,
                5,
                12884921436,
                "uvm_build_phase",
                3852,
                279,
                6,
                6,
                12884921593,
                "uvm_connect_phase",
                3852,
                279,
                6,
                6,
                12884921635,
                "uvm_end_of_elaboration_phase",
                3883,
                277,
                6,
                6,
                12884921674,
                "uvm_start_of_simulation_phase",
                3852,
                279,
                6,
                6,
                12884921718,
                "uvm_run_phase",
                3687,
                276,
                7,
                6,
                12884921784,
                "uvm_extract_phase",
                3881,
                277,
                6,
                6,
                12884921827,
                "uvm_check_phase",
                3881,
                277,
                6,
                6,
                12884921862,
                "uvm_report_phase",
                3852,
                279,
                6,
                6,
                12884921898,
                "uvm_final_phase",
                3881,
                277,
                6,
                6,
                12884921936,
                "uvm_pre_reset_phase",
                3837,
                276,
                6,
                6,
                12884922020,
                "uvm_reset_phase",
                3837,
                276,
                6,
                6,
                12884922065,
                "uvm_post_reset_phase",
                3837,
                276,
                6,
                6,
                12884922103,
                "uvm_pre_configure_phase",
                3837,
                276,
                6,
                6,
                12884922143,
                "uvm_configure_phase",
                3837,
                276,
                6,
                6,
                12884922182,
                "uvm_post_configure_phase",
                3837,
                276,
                6,
                6,
                12884922221,
                "uvm_pre_main_phase",
                3837,
                276,
                6,
                6,
                12884922257,
                "uvm_main_phase",
                3837,
                276,
                6,
                6,
                12884922297,
                "uvm_post_main_phase",
                3837,
                276,
                6,
                6,
                12884922333,
                "uvm_pre_shutdown_phase",
                3837,
                276,
                6,
                6,
                12884922369,
                "uvm_shutdown_phase",
                3837,
                276,
                6,
                6,
                12884922408,
                "uvm_post_shutdown_phase",
                3837,
                276,
                6,
                6,
                12884922448,
                "uvm_bottomup_phase",
                7698,
                672,
                4,
                4,
                12884921183,
                "uvm_topdown_phase",
                8533,
                801,
                4,
                4,
                12884921297,
                "uvm_sequence_base",
                52060,
                4671,
                86,
                53,
                12884938343,
                "uvm_sequence_item",
                30178,
                2434,
                32,
                32,
                12884935175,
                "uvm_port_component_base",
                4202,
                240,
                9,
                9,
                12884930546,
                "uvm_root_report_handler",
                2000,
                97,
                3,
                3,
                12884924429,
                "uvm_config_object_wrapper",
                763,
                41,
                2,
                2,
                12884926645,
                "uvm_objection_context_object",
                2273,
                281,
                3,
                3,
                12884928671,
                "uvm_objection_callback",
                2946,
                131,
                5,
                5,
                12884928773,
                "uvm_callbacks_objection",
                3587,
                192,
                6,
                6,
                12884928705,
                "uvm_objection_events",
                763,
                41,
                2,
                2,
                12884927331,
                "uvm_heartbeat_callback",
                3712,
                265,
                6,
                6,
                12884929099,
                "uvm_heartbeat",
                5369,
                286,
                12,
                12,
                12884928864,
                "uvm_cmd_line_verb",
                673,
                36,
                2,
                2,
                12884929621,
                "uvm_tlm_event",
                673,
                36,
                2,
                2,
                12884932715,
                "uvm_monitor",
                2070,
                135,
                4,
                4,
                12884934605,
                "uvm_scoreboard",
                2070,
                135,
                4,
                4,
                12884934853,
                "uvm_agent",
                5006,
                420,
                6,
                6,
                12884934914,
                "uvm_test",
                2070,
                135,
                4,
                4,
                12884935091,
                "uvm_sequence_request",
                763,
                41,
                2,
                2,
                12884937290,
                "uvm_sequence_library_cfg",
                7058,
                550,
                9,
                9,
                12884939896,
                "uvm_tlm_time",
                5157,
                343,
                12,
                12,
                12884940769,
                "uvm_tlm_extension_base",
                2820,
                134,
                6,
                6,
                12884942064,
                "uvm_tlm_generic_payload",
                75741,
                8864,
                49,
                48,
                12884941176,
                "uvm_reg_field",
                47139,
                3286,
                62,
                61,
                12884946189,
                "uvm_vreg_field",
                22074,
                1512,
                32,
                32,
                12884948221,
                "uvm_reg",
                63484,
                4321,
                89,
                89,
                12884949216,
                "uvm_reg_file",
                19785,
                1443,
                21,
                21,
                12884953005,
                "uvm_vreg",
                29610,
                2033,
                45,
                45,
                12884954596,
                "uvm_reg_block",
                46447,
                2954,
                72,
                72,
                12884960971,
                "uvm_mem",
                58920,
                4117,
                73,
                73,
                12884956131,
                "uvm_reg_item",
                15474,
                1632,
                12,
                11,
                12884943881,
                "uvm_reg_map",
                117632,
                11696,
                99,
                62,
                12884958557,
                "uvm_reg_map_info",
                673,
                36,
                2,
                2,
                12884958528,
                "uvm_reg_adapter",
                4459,
                338,
                6,
                6,
                12884944197,
                "uvm_reg_indirect_data",
                10372,
                473,
                19,
                19,
                12884952365,
                "uvm_hdl_path_concat",
                3737,
                305,
                5,
                5,
                12884943770,
                "uvm_reg_tlm_adapter",
                18344,
                1842,
                11,
                11,
                12884944328,
                "uvm_predict_s",
                673,
                36,
                2,
                2,
                12884944453,
                "uvm_reg_backdoor",
                14808,
                821,
                26,
                26,
                12884945800,
                "uvm_reg_cbs",
                4577,
                226,
                9,
                9,
                12884945275,
                "uvm_reg_read_only_cbs",
                8706,
                533,
                13,
                13,
                12884945600,
                "uvm_reg_write_only_cbs",
                8706,
                533,
                13,
                13,
                12884945686,
                "uvm_vreg_field_cbs",
                4148,
                268,
                6,
                6,
                12884948550,
                "uvm_reg_fifo",
                5951,
                326,
                14,
                13,
                12884952693,
                "uvm_mem_mam_cfg",
                673,
                36,
                3,
                2,
                12884954084,
                "uvm_mem_region",
                8498,
                424,
                16,
                16,
                12884953798,
                "uvm_mem_mam_policy",
                673,
                36,
                3,
                2,
                12884954042,
                "uvm_mem_mam",
                4918,
                234,
                10,
                10,
                12884953586,
                "uvm_vreg_cbs",
                4023,
                246,
                6,
                6,
                12884955153,
                "snps_uvm_reg_bank_group",
                9853,
                663,
                17,
                17,
                12884965629,
                "snps_uvm_reg_banked",
                5601,
                257,
                10,
                10,
                12884965767,
                "snps_uvm_reg_bank_set",
                1420,
                66,
                3,
                3,
                12884965736,
                "snps_uvm_reg_map",
                7627,
                489,
                11,
                11,
                12884966017
            ],
            "child_modules": {},
            "Compiled Times": 1,
            "Compiled": "Yes",
            "end_perf": [
                6.2738320827484131,
                5.781612,
                0.34761500000000001,
                349244,
                351996,
                304745556593127,
                12884901889,
                0
            ],
            "nMops": 200456,
            "nQuads": 62496,
            "nRouts": 2753
        },
        "_vcs_msglog": {
            "start_perf": [
                6.2744019031524658,
                5.7821009999999999,
                0.34764499999999998,
                349244,
                351996,
                1658908887.9062729,
                304745557966973
            ],
            "child_modules": {},
            "Compiled Times": 1,
            "Compiled": "Yes",
            "nMops": 34,
            "end_perf": [
                6.2763500213623047,
                5.7839390000000002,
                0.34775499999999998,
                349244,
                351996,
                304745563596772,
                17179869185,
                0
            ],
            "nQuads": 23,
            "nRouts": 9
        },
        "uvm_custom_install_recording": {
            "start_perf": [
                6.2763869762420654,
                5.7839770000000001,
                0.34775800000000001,
                349244,
                351996,
                1658908887.908258,
                304745563649610
            ],
            "svclass": [
                "uvm_vcs_recorder",
                11921,
                812,
                17,
                17,
                21474836512,
                "msglog_msgname",
                1307,
                107,
                2,
                2,
                21474836655,
                "msglog",
                17844,
                1704,
                11,
                11,
                21474836691,
                "vcs_smartlog_catcher",
                11562,
                767,
                4,
                4,
                21474836841,
                "uvm_pkg_uvm_object_registry_245147496162194765_101",
                7219,
                520,
                11,
                11,
                12884907648
            ],
            "child_modules": {},
            "Compiled Times": 1,
            "Compiled": "Yes",
            "end_perf": [
                6.3290159702301025,
                5.8364240000000001,
                0.34778599999999998,
                349244,
                351996,
                304745716079714,
                21474836481,
                0
            ],
            "nMops": 6481,
            "nQuads": 2552,
            "nRouts": 112
        },
        "uvm_custom_install_verdi_recording": {
            "start_perf": [
                6.3290760517120361,
                5.8364830000000003,
                0.34778999999999999,
                349244,
                351996,
                1658908887.960947,
                304745716165293
            ],
            "svclass": [
                "uvm_custom_install_verdi_recording__vcs_type_T_17516288123831238565_54_42098745823728729451_7",
                0,
                0,
                0,
                0,
                0,
                "uvm_custom_install_verdi_recording__vcs_type_T_17516288123831238565_54_17604091792765680068_12",
                0,
                0,
                0,
                0,
                0,
                "uvm_custom_install_verdi_recording__vcs_type_T_33888099752757866797_48_29057405201454559803_10",
                0,
                0,
                0,
                0,
                0,
                "uvm_custom_install_verdi_recording__vcs_type_T_33000166982961514326_48_29057405201454559803_10",
                0,
                0,
                0,
                0,
                0,
                "uvm_custom_install_verdi_recording__vcs_type_T_17516288123831238565_54_29057405201454559803_10",
                0,
                0,
                0,
                0,
                0,
                "_vcs_struct_rsrc_msg_struct",
                0,
                0,
                0,
                0,
                0,
                "uvm_verdi_pli_base",
                13722,
                882,
                28,
                28,
                25769803904,
                "verdi_cmdline_processor",
                28182,
                2781,
                26,
                26,
                25769804133,
                "uvm_verdi_recorder",
                54092,
                5215,
                23,
                23,
                25769804460,
                "uvm_map_access_recorder",
                26957,
                2644,
                11,
                11,
                25769805285,
                "verdi_report_catcher",
                139921,
                13975,
                19,
                19,
                25769806076,
                "uvm_dhier_component",
                6148,
                450,
                7,
                7,
                25769808695,
                "uvm_verdi_pli",
                22420,
                1453,
                27,
                27,
                25769808828,
                "uvm_pkg_uvm_component_registry_234631716908298885_119",
                7045,
                501,
                11,
                11,
                12884907517
            ],
            "child_modules": {},
            "Compiled Times": 1,
            "Compiled": "Yes",
            "significant_routs": [
                [
                    292,
                    "F_VCSgd_EbjT3_128_0",
                    190861441,
                    116488,
                    11605
                ]
            ],
            "nQuads": 16329,
            "nMops": 44295,
            "end_perf": [
                6.6217451095581055,
                6.1171559999999996,
                0.359597,
                349244,
                351996,
                304746563475838,
                25769803777,
                0
            ],
            "nRouts": 513
        },
        "accum": {
            "start_perf": [
                6.6218409538269043,
                6.117248,
                0.35960300000000001,
                349244,
                351996,
                1658908888.2537119,
                304746563636121
            ],
            "child_modules": {},
            "Compiled Times": 1,
            "Compiled": "Yes",
            "nMops": 128,
            "end_perf": [
                6.6247830390930176,
                6.120025,
                0.35976599999999997,
                349244,
                351996,
                304746572222673,
                30064771073,
                0
            ],
            "nQuads": 71,
            "nRouts": 20
        },
        "accum_if": {
            "start_perf": [
                6.6248259544372559,
                6.1200679999999998,
                0.35976799999999998,
                349244,
                351996,
                1658908888.2566969,
                304746572279339
            ],
            "svclass": [
                "accum_if_vcs_virt_intf_C",
                0,
                0,
                0,
                0,
                0
            ],
            "child_modules": {},
            "Compiled Times": 1,
            "Compiled": "Yes",
            "end_perf": [
                6.6262040138244629,
                6.1200679999999998,
                0.36114600000000002,
                349244,
                351996,
                304746576328986,
                34359738369,
                0
            ],
            "nMops": 19,
            "nQuads": 6,
            "nRouts": 7
        },
        "top_tb": {
            "start_perf": [
                6.6262469291687012,
                6.1200679999999998,
                0.36118899999999998,
                349244,
                351996,
                1658908888.2581179,
                304746576385768
            ],
            "child_modules": {
                "accum": 1,
                "accum_if": 2
            },
            "Compiled Times": 1,
            "Compiled": "Yes",
            "nMops": 526,
            "end_perf": [
                6.6310489177703857,
                6.1223919999999996,
                0.36366599999999999,
                349244,
                351996,
                304746590358722,
                38654705665,
                0
            ],
            "nQuads": 199,
            "nRouts": 34
        }
    },
    "ObjArchives": [
        {
            "archive": "archive.0/_115596_archive_1.a",
            "objects": [
                [
                    "hEeZs_d.o",
                    6778422
                ],
                [
                    "uM9F1_d.o",
                    19492
                ],
                [
                    "pjuRd_d.o",
                    226384
                ],
                [
                    "reYIK_d.o",
                    44340
                ],
                [
                    "zr7M1_d.o",
                    6000804
                ],
                [
                    "zQBzV_d.o",
                    10666
                ],
                [
                    "nhiwz_d.o",
                    358016
                ],
                [
                    "EbjT3_d.o",
                    1236402
                ],
                [
                    "DiISD_d.o",
                    9460
                ],
                [
                    "v7YNK_d.o",
                    11748
                ],
                [
                    "W0eJz_d.o",
                    21494
                ],
                [
                    "amcQwB.o",
                    428292
                ]
            ],
            "size": 15145520
        }
    ],
    "reusePaths": {},
    "stat": {
        "ru_self_end": {
            "ru_nivcsw": 623,
            "ru_nvcsw": 7,
            "ru_utime_sec": 6.1261159999999997,
            "ru_stime_sec": 0.36764599999999997,
            "ru_maxrss_kb": 185876,
            "ru_majflt": 0,
            "ru_minflt": 41523
        },
        "ru_childs_end": {
            "ru_nivcsw": 29,
            "ru_nvcsw": 17,
            "ru_utime_sec": 0.013032,
            "ru_stime_sec": 0.0041939999999999998,
            "ru_maxrss_kb": 83820,
            "ru_majflt": 0,
            "ru_minflt": 3382
        },
        "cpu_cycles_end": 304746612720883,
        "peak_mem_kb": 351996
    }
}